LICENSE
MANIFEST.in
README.md
pyproject.toml
src/catmining/__init__.py
src/catmining/download.py
src/catmining/multiturn.py
src/catmining/multiturn_helpers.py
src/catmining/preprocess.py
src/catmining/prompts.py
src/catmining/py.typed
src/catmining.egg-info/PKG-INFO
src/catmining.egg-info/SOURCES.txt
src/catmining.egg-info/dependency_links.txt
src/catmining.egg-info/requires.txt
src/catmining.egg-info/top_level.txt
src/catmining/__pycache__/__init__.cpython-311.pyc
src/catmining/__pycache__/download.cpython-311.pyc
src/catmining/__pycache__/extract.cpython-311.pyc
src/catmining/__pycache__/functions.cpython-311.pyc
src/catmining/__pycache__/multiturn.cpython-311.pyc
src/catmining/__pycache__/multiturn_helpers.cpython-311.pyc
src/catmining/__pycache__/preprocess.cpython-311.pyc
src/catmining/__pycache__/prompts.cpython-311.pyc