Metadata-Version: 2.4
Name: catmining
Version: 0.0.1
Summary: A packaged form of the CatMiner workflow written by Walls and Linic.
Author-email: Benjamin Walls <benwalls2000@gmail.com>
License: BSD-3
Project-URL: repository, https://github.com/benjww/CatMiner
Keywords: Catalysis,Text Mining
Classifier: Development Status :: 4 - Beta
Classifier: Intended Audience :: Science/Research
Classifier: Programming Language :: Python :: 3
Classifier: Programming Language :: Python :: 3.10
Classifier: Programming Language :: Python :: 3.11
Classifier: Programming Language :: Python :: 3.12
Classifier: Programming Language :: Python :: 3.13
Classifier: Intended Audience :: Science/Research
Classifier: Topic :: Scientific/Engineering
Classifier: Operating System :: Microsoft :: Windows
Classifier: Operating System :: Unix
Classifier: Operating System :: MacOS
Requires-Python: >=3.9
License-File: LICENSE
Requires-Dist: pandas
Provides-Extra: dev
Requires-Dist: boto3>=1.40.18; extra == "dev"
Requires-Dist: openai>=1.78.1; extra == "dev"
Requires-Dist: fireworks-ai>=0.19.18; extra == "dev"
Requires-Dist: chemdataextractor2>=2.4.0; extra == "dev"
Provides-Extra: docs
Requires-Dist: mkdocs-material>=9.4.0; extra == "docs"
Requires-Dist: mkdocstrings[python]>=0.22.0; extra == "docs"
Requires-Dist: mkdocs-gen-files>=0.5.0; extra == "docs"
Requires-Dist: mkdocs-literate-nav>=0.6.0; extra == "docs"
Requires-Dist: pillow>=10.0.0; extra == "docs"
Requires-Dist: cairosvg>=2.7.1; extra == "docs"
Dynamic: license-file
